codegrab/__init__.py
codegrab/__main__.py
codegrab/cli.py
codegrab-0.1.2.dist-info/METADATA
codegrab-0.1.2.dist-info/WHEEL
codegrab-0.1.2.dist-info/entry_points.txt
codegrab-0.1.2.dist-info/licenses/LICENSE
codegrab-0.1.2.dist-info/RECORD
