Metadata-Version: 2.4
Name: codegrab
Version: 0.1.2
Summary: A command line tool to fetch code from github for AI purposes.
Project-URL: Homepage, https://github.com/geirfreysson/codegrab
Project-URL: Changelog, https://github.com/geirfreysson/codegrab/releases
Project-URL: Issues, https://github.com/geirfreysson/codegrab/issues
Project-URL: CI, https://github.com/geirfreysson/codegrab/actions
Author: Geir Freysson
License: Apache-2.0
License-File: LICENSE
Classifier: License :: OSI Approved :: Apache Software License
Requires-Python: >=3.8
Requires-Dist: click
Requires-Dist: requests>=2.32.3
Provides-Extra: test
Requires-Dist: pytest; extra == 'test'
